cryptonest/__init__.py
cryptonest/__main__.py
cryptonest/crypto.py
cryptonest/cryptonest.py
cryptonest-0.1.0.dist-info/METADATA
cryptonest-0.1.0.dist-info/WHEEL
cryptonest-0.1.0.dist-info/top_level.txt
cryptonest-0.1.0.dist-info/RECORD
